FoKL/FoKLRoutines.py
FoKL/GP_Integrate.py
FoKL/__init__.py
FoKL/getKernels.py
FoKL/kernels/BernoulliPolynomials_20_orthonormal.txt
FoKL/kernels/BernoulliPolynomials_20_orthonormal_scaled.txt
FoKL/kernels/splineCoefficient500_highPrecision_smoothed.txt
FoKL_beta-1.2.4.dist-info/LICENSE
FoKL_beta-1.2.4.dist-info/METADATA
FoKL_beta-1.2.4.dist-info/WHEEL
FoKL_beta-1.2.4.dist-info/top_level.txt
FoKL_beta-1.2.4.dist-info/RECORD
