Metadata-Version: 2.1
Name: FoKL-beta
Version: 1.2.4
Summary: Karhunen Loève decomposed Gaussian processes with forward variable selection
Author-email: ESMS Group <derek.slack.001@gmail.com>
Classifier: Programming Language :: Python :: 3
Requires-Python: >=3.8
License-File: LICENSE
Requires-Dist: requests
Requires-Dist: Pyomo >=6.7.0
Requires-Dist: importlib-metadata ; python_version < "3.8"
